ConnectWiseManageAPI/CWFunctions.py
ConnectWiseManageAPI/__init__.py
ConnectWiseManageAPI-0.3.9.dist-info/METADATA
ConnectWiseManageAPI-0.3.9.dist-info/WHEEL
ConnectWiseManageAPI-0.3.9.dist-info/top_level.txt
ConnectWiseManageAPI-0.3.9.dist-info/RECORD
