Metadata-Version: 2.1
Name: ConnectWiseManageAPI
Version: 0.3.9
Summary: CWManageAPI Python Wrapper
Home-page: UNKNOWN
Author: lillevikit
License: UNKNOWN
Keywords: python,API,ConnectWise,Manage,CWManage
Platform: UNKNOWN
Classifier: Development Status :: 1 - Planning
Classifier: Intended Audience :: Developers
Classifier: Programming Language :: Python :: 3
Classifier: Operating System :: Unix
Classifier: Operating System :: MacOS :: MacOS X
Classifier: Operating System :: Microsoft :: Windows
Requires-Dist: ConnectWiseManageAPI
